mohan/Similarity.py
mohan/__init__.py
mohan/_version.py
Mohan-0.0.7a0.dist-info/LICENSE
Mohan-0.0.7a0.dist-info/METADATA
Mohan-0.0.7a0.dist-info/WHEEL
Mohan-0.0.7a0.dist-info/top_level.txt
Mohan-0.0.7a0.dist-info/RECORD
