Metadata-Version: 2.2
Name: Mohan
Version: 0.0.7a0
Summary: Colav Similarity Search Engine
Home-page: https://github.com/colav/Mohan
Author: Colav
Author-email: colav@udea.edu.co
License: BSD
License-File: LICENSE
Requires-Dist: elasticsearch
Requires-Dist: hunahpu
Requires-Dist: unidecode
Dynamic: author
Dynamic: author-email
Dynamic: description
Dynamic: description-content-type
Dynamic: home-page
Dynamic: license
Dynamic: requires-dist
Dynamic: summary
